odoo/addons/hr_expense_tier_validation/README.rst
odoo/addons/hr_expense_tier_validation/__init__.py
odoo/addons/hr_expense_tier_validation/__manifest__.py
odoo/addons/hr_expense_tier_validation/data/ir_config_parameter.xml
odoo/addons/hr_expense_tier_validation/i18n/hr_expense_tier_validation.pot
odoo/addons/hr_expense_tier_validation/i18n/it.po
odoo/addons/hr_expense_tier_validation/models/__init__.py
odoo/addons/hr_expense_tier_validation/models/hr_expense.py
odoo/addons/hr_expense_tier_validation/models/hr_expense_sheet.py
odoo/addons/hr_expense_tier_validation/models/tier_definition.py
odoo/addons/hr_expense_tier_validation/readme/CONFIGURE.md
odoo/addons/hr_expense_tier_validation/readme/CONTRIBUTORS.md
odoo/addons/hr_expense_tier_validation/readme/DESCRIPTION.md
odoo/addons/hr_expense_tier_validation/readme/USAGE.md
odoo/addons/hr_expense_tier_validation/static/description/icon.png
odoo/addons/hr_expense_tier_validation/static/description/index.html
odoo/addons/hr_expense_tier_validation/tests/__init__.py
odoo/addons/hr_expense_tier_validation/tests/test_hr_expense_tier_validation.py
odoo/addons/hr_expense_tier_validation/views/hr_expense_sheet_view.xml
odoo_addon_hr_expense_tier_validation-18.0.1.0.0.2.dist-info/METADATA
odoo_addon_hr_expense_tier_validation-18.0.1.0.0.2.dist-info/WHEEL
odoo_addon_hr_expense_tier_validation-18.0.1.0.0.2.dist-info/top_level.txt
odoo_addon_hr_expense_tier_validation-18.0.1.0.0.2.dist-info/RECORD
